entropytriangle/__init__.py
entropytriangle/auxfunc.py
entropytriangle/coordsentropic.py
entropytriangle/entropytriangle.py
entropytriangle/jentropies.py
entropytriangle/sentropies.py
entropytriangle/ternary/__init__.py
entropytriangle/ternary/colormapping.py
entropytriangle/ternary/heatmapping.py
entropytriangle/ternary/helpers.py
entropytriangle/ternary/lines.py
entropytriangle/ternary/plotting.py
entropytriangle/ternary/ternary_axes_subplot.py
entropytriangle-1.0.2.dist-info/LICENSE.txt
entropytriangle-1.0.2.dist-info/METADATA
entropytriangle-1.0.2.dist-info/RECORD
entropytriangle-1.0.2.dist-info/WHEEL
entropytriangle-1.0.2.dist-info/top_level.txt
